docling_enhanced/__init__.py
docling_enhanced/_version.py
docling_enhanced/py.typed
docling_enhanced/models/__init__.py
docling_enhanced/models/enhanced_document_picture_classifier.py
docling_enhanced/models/enhanced_layout_model.py
docling_enhanced/models/enhanced_table_structure_model.py
docling_enhanced/utils/__init__.py
docling_enhanced/utils/enhanced_model_utils.py
docling_enhanced_onnx-1.0.0.dist-info/licenses/LICENSE
docling_enhanced_onnx-1.0.0.dist-info/METADATA
docling_enhanced_onnx-1.0.0.dist-info/WHEEL
docling_enhanced_onnx-1.0.0.dist-info/top_level.txt
docling_enhanced_onnx-1.0.0.dist-info/RECORD
