Metadata-Version: 2.4
Name: docling-enhanced-onnx
Version: 1.0.0
Summary: Enhanced Docling Models with ONNX Auto-Detection and Air-Gapped Support
Author-email: Asep Muhamad <asepmuhamad@gmail.com>
Maintainer-email: Asep Muhamad <asepmuhamad@gmail.com>
License: MIT
Project-URL: Homepage, https://github.com/asmud/docling
Project-URL: Documentation, https://github.com/asmud/docling#readme
Project-URL: Repository, https://github.com/asmud/docling.git
Project-URL: Issues, https://github.com/asmud/docling/issues
Project-URL: Changelog, https://github.com/asmud/docling/blob/main/CHANGELOG.md
Keywords: docling,onnx,document-processing,table-extraction,layout-analysis,air-gapped,machine-learning,ai
Classifier: Development Status :: 4 - Beta
Classifier: Intended Audience :: Developers
Classifier: Intended Audience :: Science/Research
Classifier: License :: OSI Approved :: MIT License
Classifier: Operating System :: OS Independent
Classifier: Programming Language :: Python :: 3
Classifier: Programming Language :: Python :: 3.10
Classifier: Programming Language :: Python :: 3.11
Classifier: Programming Language :: Python :: 3.12
Classifier: Topic :: Scientific/Engineering :: Artificial Intelligence
Classifier: Topic :: Software Development :: Libraries :: Python Modules
Classifier: Topic :: Text Processing :: General
Requires-Python: >=3.10
License-File: LICENSE
Requires-Dist: docling>=2.0.0
Requires-Dist: onnxruntime>=1.15.0
Requires-Dist: numpy>=1.21.0
Requires-Dist: pillow>=8.3.0
Requires-Dist: pydantic>=2.0.0
Requires-Dist: typing-extensions>=4.0.0
Provides-Extra: dev
Requires-Dist: pytest>=7.0.0; extra == "dev"
Requires-Dist: pytest-cov>=4.0.0; extra == "dev"
Requires-Dist: black>=23.0.0; extra == "dev"
Requires-Dist: isort>=5.12.0; extra == "dev"
Requires-Dist: flake8>=6.0.0; extra == "dev"
Requires-Dist: mypy>=1.5.0; extra == "dev"
Requires-Dist: pre-commit>=3.0.0; extra == "dev"
Provides-Extra: test
Requires-Dist: pytest>=7.0.0; extra == "test"
Requires-Dist: pytest-cov>=4.0.0; extra == "test"
Requires-Dist: pytest-mock>=3.10.0; extra == "test"
Provides-Extra: gpu
Requires-Dist: onnxruntime-gpu>=1.15.0; extra == "gpu"
Provides-Extra: onnx
Requires-Dist: docling-onnx-models>=1.0.0; extra == "onnx"
Provides-Extra: full
Requires-Dist: docling-onnx-models>=1.0.0; extra == "full"
Requires-Dist: onnxruntime-gpu>=1.15.0; extra == "full"
Dynamic: license-file
